bscli/__init__.py
bscli/cli.py
bscli/config.py
bscli/course_plugin.py
bscli/downloader.py
bscli/filesender.py
bscli/logs.py
bscli/main.py
bscli/oauth.py
bscli/progress.py
bscli/utils.py
bscli/version_check.py
bscli/commands/__init__.py
bscli/commands/base.py
bscli/commands/config.py
bscli/commands/assignments/__init__.py
bscli/commands/assignments/check_grading_groups.py
bscli/commands/assignments/distribute.py
bscli/commands/assignments/download.py
bscli/commands/assignments/find_grader.py
bscli/commands/assignments/grading_progress.py
bscli/commands/assignments/list.py
bscli/commands/assignments/list_deadlines.py
bscli/commands/assignments/list_division.py
bscli/commands/assignments/list_graders.py
bscli/commands/assignments/list_submissions.py
bscli/commands/courses/__init__.py
bscli/commands/courses/create_config.py
bscli/commands/courses/list.py
bscli/commands/feedback/__init__.py
bscli/commands/feedback/upload.py
bscli/data/grader/readme.txt
bscli/data/grader/data/bash-grading.sh
bscli/data/grader/data/persist_token.sh
bscli/data/grader/data/upload-virtualenv.sh
bscli/data/schema/bsapi.schema.json
bscli/data/schema/course.schema.json
bscli/data/schema/filesender.schema.json
bscli/division/__init__.py
bscli/division/brightspace.py
bscli/division/persistent.py
bscli/division/random_divider.py
bscli/filesender_client/__init__.py
bscli/filesender_client/filesender.py
bscli/processing/__init__.py
bscli/processing/utils.py
bscli/processing/graders/__init__.py
bscli/processing/graders/api_config.py
bscli/processing/graders/create_archive.py
bscli/processing/graders/feedback_template.py
bscli/processing/graders/grader_config.py
bscli/processing/graders/grading_instructions.py
bscli/processing/submissions/__init__.py
bscli/processing/submissions/docx_to_pdf.py
bscli/processing/submissions/extract_archives.py
bscli/processing/submissions/fix_permissions.py
bscli/processing/submissions/flatten.py
bscli/processing/submissions/inject_files.py
bscli-0.3.7.dist-info/licenses/LICENSE
bscli-0.3.7.dist-info/METADATA
bscli-0.3.7.dist-info/WHEEL
bscli-0.3.7.dist-info/entry_points.txt
bscli-0.3.7.dist-info/top_level.txt
bscli-0.3.7.dist-info/RECORD
