Metadata-Version: 2.4
Name: bscli
Version: 0.3.7
Summary: Brightspace CLI, grading automation and management system.
Author-email: Job Doesburg <Job.Doesburg@ru.nl>, Ciske Harsema <Ciske.Harsema@ru.nl>
License: MIT License
Requires-Python: >=3.10
License-File: LICENSE
Requires-Dist: brightspace-api>=2.1.0
Requires-Dist: patool
Requires-Dist: jsonschema
Dynamic: license-file
